neuralgym/__init__.py
neuralgym/callbacks/__init__.py
neuralgym/callbacks/callbacks.py
neuralgym/callbacks/hyper_param_scheduler.py
neuralgym/callbacks/model_restorer.py
neuralgym/callbacks/model_saver.py
neuralgym/callbacks/model_sync.py
neuralgym/callbacks/npz_model_loader.py
neuralgym/callbacks/secondary_multigpu_trainer.py
neuralgym/callbacks/secondary_trainer.py
neuralgym/callbacks/summary_writer.py
neuralgym/callbacks/weights_viewer.py
neuralgym/data/__init__.py
neuralgym/data/data_from_fnames.py
neuralgym/data/dataset.py
neuralgym/data/feeding_queue_runner.py
neuralgym/models/__init__.py
neuralgym/models/model.py
neuralgym/ops/__init__.py
neuralgym/ops/gan_ops.py
neuralgym/ops/image_ops.py
neuralgym/ops/layers.py
neuralgym/ops/loss_ops.py
neuralgym/ops/summary_ops.py
neuralgym/ops/train_ops.py
neuralgym/server/__init__.py
neuralgym/train/__init__.py
neuralgym/train/multigpu_trainer.py
neuralgym/train/trainer.py
neuralgym/utils/__init__.py
neuralgym/utils/config.py
neuralgym/utils/data_utils.py
neuralgym/utils/gpus.py
neuralgym/utils/logger.py
neuralgym/utils/tf_utils.py
neuralgym011-0.1.1.dist-info/LICENSE
neuralgym011-0.1.1.dist-info/METADATA
neuralgym011-0.1.1.dist-info/WHEEL
neuralgym011-0.1.1.dist-info/top_level.txt
neuralgym011-0.1.1.dist-info/RECORD
